doloris/__init__.py
doloris/__main__.py
doloris/algorithm.py
doloris/panel.py
doloris/src/__init__.py
doloris/src/plot.py
doloris/src/data/__init__.py
doloris/src/data/dataloader.py
doloris/src/data/label.py
doloris/src/data/process.py
doloris/src/model/__init__.py
doloris/src/model/algorithms.py
doloris/src/model/evaluate.py
doloris/src/model/models.py
doloris/src/model/train.py
doloris-1.1.0.dist-info/licenses/LICENSE
doloris-1.1.0.dist-info/METADATA
doloris-1.1.0.dist-info/WHEEL
doloris-1.1.0.dist-info/entry_points.txt
doloris-1.1.0.dist-info/top_level.txt
doloris-1.1.0.dist-info/RECORD
