Metadata-Version: 2.4
Name: doloris
Version: 1.1.0
Summary: Detection Of Learning Obstacles via Risk-aware Interaction Signals
Author-email: 许睿林 <xurlin5@mail2.sysu.edu.cn>, 傅小桐 <fuxt5@mail2.sysu.edu.cn>
License-Expression: MIT
Requires-Python: >=3.12
License-File: LICENSE
Requires-Dist: gradio
Requires-Dist: pandas
Requires-Dist: tqdm
Requires-Dist: scikit-learn
Requires-Dist: seaborn
Requires-Dist: numba
Dynamic: license-file
